setup.cfg
setup.py
Autism_Treatment_Assistance/__init__.py
Autism_Treatment_Assistance/ata
Autism_Treatment_Assistance.egg-info/PKG-INFO
Autism_Treatment_Assistance.egg-info/SOURCES.txt
Autism_Treatment_Assistance.egg-info/dependency_links.txt
Autism_Treatment_Assistance.egg-info/requires.txt
Autism_Treatment_Assistance.egg-info/top_level.txt