Metadata-Version: 1.1
Name: Autism-Treatment-Assistance
Version: 0.4
Summary: Employs data science and deep learning to assist therapists treat a common autism symptom that involves interpretation and correlation of facial and speech emotions
Home-page: https://github.com/ParhamP/Autism_Treatment_Assistance
Author: Parham Pourdavood
Author-email: ppourdavood@gmail.com
License: Apache-2.0
Download-URL: https://github.com/ParhamP/Autism_Treatment_Assistance/tarball/0.1
Keywords: data science, emotion recognition, psychology, autism, speech emotion recognition
Platform: UNKNOWN
